{
  "type": "excalidraw",
  "version": 2,
  "source": "/data/projects/accordo/demo/state-basic.mmd",
  "mermaidSource": "stateDiagram-v2\n    [*] --> Idle\n    Idle --> Active : start\n    Active --> Idle : stop\n    Active --> [*] : terminate",
  "elements": [
    {
      "id": "5bde435b-3084-4783-8785-c7e895355383",
      "kind": "node",
      "type": "ellipse",
      "x": 75,
      "y": 0,
      "width": 30,
      "height": 30,
      "roughness": 1,
      "backgroundColor": "transparent",
      "strokeColor": "#1e1e1e",
      "strokeWidth": 1,
      "strokeStyle": "solid",
      "fillStyle": "hachure",
      "opacity": 100,
      "version": 1,
      "versionNonce": 660417475,
      "isDeleted": false,
      "angle": 0,
      "seed": 126557790,
      "groupIds": [],
      "frameId": null,
      "updated": 1775538137009,
      "link": null,
      "locked": false,
      "fontFamily": 1,
      "roundness": null,
      "boundElements": [
        {
          "id": "76b830fe-d9dd-4576-a787-b9a3136ae3ab",
          "type": "text"
        },
        {
          "id": "a17f86cb-d9e3-4910-b242-4bb06a34cf10",
          "type": "arrow"
        }
      ],
      "containerId": null,
      "customData": {
        "mermaidId": "root_start",
        "kind": "node"
      }
    },
    {
      "id": "76b830fe-d9dd-4576-a787-b9a3136ae3ab",
      "kind": "label",
      "type": "text",
      "x": 75,
      "y": 5,
      "width": 30,
      "height": 20,
      "roughness": 1,
      "fontSize": 16,
      "strokeColor": "#1e1e1e",
      "version": 1,
      "versionNonce": 3574400914,
      "isDeleted": false,
      "fillStyle": "hachure",
      "strokeWidth": 1,
      "strokeStyle": "solid",
      "opacity": 100,
      "angle": 0,
      "seed": 711225515,
      "groupIds": [],
      "frameId": null,
      "updated": 1775538137009,
      "link": null,
      "locked": false,
      "backgroundColor": "transparent",
      "fontFamily": 1,
      "roundness": null,
      "boundElements": null,
      "containerId": "5bde435b-3084-4783-8785-c7e895355383",
      "customData": {
        "mermaidId": "root_start:text",
        "kind": "label"
      },
      "text": "root_start",
      "textAlign": "center",
      "verticalAlign": "middle",
      "originalText": "root_start",
      "lineHeight": 1.25
    },
    {
      "id": "c6ac4bab-659a-440a-8c35-3247f9d17e2c",
      "kind": "node",
      "type": "rectangle",
      "x": 0,
      "y": 110,
      "width": 180,
      "height": 60,
      "roughness": 1,
      "backgroundColor": "transparent",
      "strokeColor": "#1e1e1e",
      "strokeWidth": 1,
      "strokeStyle": "solid",
      "fillStyle": "hachure",
      "opacity": 100,
      "version": 1,
      "versionNonce": 1750241466,
      "isDeleted": false,
      "angle": 0,
      "seed": 1168775091,
      "groupIds": [],
      "frameId": null,
      "updated": 1775538137009,
      "link": null,
      "locked": false,
      "fontFamily": 1,
      "roundness": {
        "type": 2
      },
      "boundElements": [
        {
          "id": "a22f5de3-d2ef-4148-b23c-8b8f8d16a287",
          "type": "text"
        },
        {
          "id": "a17f86cb-d9e3-4910-b242-4bb06a34cf10",
          "type": "arrow"
        },
        {
          "id": "35acc28e-f29f-469f-a9ff-60aca8d8dfb7",
          "type": "arrow"
        },
        {
          "id": "e2e77f92-16e6-4e37-94be-68a0309160b1",
          "type": "arrow"
        }
      ],
      "containerId": null,
      "customData": {
        "mermaidId": "Idle",
        "kind": "node"
      }
    },
    {
      "id": "a22f5de3-d2ef-4148-b23c-8b8f8d16a287",
      "kind": "label",
      "type": "text",
      "x": 0,
      "y": 130,
      "width": 180,
      "height": 20,
      "roughness": 1,
      "fontSize": 16,
      "strokeColor": "#1e1e1e",
      "version": 1,
      "versionNonce": 631819533,
      "isDeleted": false,
      "fillStyle": "hachure",
      "strokeWidth": 1,
      "strokeStyle": "solid",
      "opacity": 100,
      "angle": 0,
      "seed": 3599251420,
      "groupIds": [],
      "frameId": null,
      "updated": 1775538137009,
      "link": null,
      "locked": false,
      "backgroundColor": "transparent",
      "fontFamily": 1,
      "roundness": null,
      "boundElements": null,
      "containerId": "c6ac4bab-659a-440a-8c35-3247f9d17e2c",
      "customData": {
        "mermaidId": "Idle:text",
        "kind": "label"
      },
      "text": "Idle",
      "textAlign": "center",
      "verticalAlign": "middle",
      "originalText": "Idle",
      "lineHeight": 1.25
    },
    {
      "id": "c6c41d29-ac84-4806-a257-694f6e77c14b",
      "kind": "node",
      "type": "rectangle",
      "x": 0,
      "y": 250,
      "width": 180,
      "height": 60,
      "roughness": 1,
      "backgroundColor": "transparent",
      "strokeColor": "#1e1e1e",
      "strokeWidth": 1,
      "strokeStyle": "solid",
      "fillStyle": "hachure",
      "opacity": 100,
      "version": 1,
      "versionNonce": 1789929430,
      "isDeleted": false,
      "angle": 0,
      "seed": 529077071,
      "groupIds": [],
      "frameId": null,
      "updated": 1775538137009,
      "link": null,
      "locked": false,
      "fontFamily": 1,
      "roundness": {
        "type": 2
      },
      "boundElements": [
        {
          "id": "0114fbc1-d011-4c03-ab41-dd1de3340c14",
          "type": "text"
        },
        {
          "id": "35acc28e-f29f-469f-a9ff-60aca8d8dfb7",
          "type": "arrow"
        },
        {
          "id": "e2e77f92-16e6-4e37-94be-68a0309160b1",
          "type": "arrow"
        },
        {
          "id": "fdcd5c32-8215-4a41-8e9d-9cc909d7df6a",
          "type": "arrow"
        }
      ],
      "containerId": null,
      "customData": {
        "mermaidId": "Active",
        "kind": "node"
      }
    },
    {
      "id": "0114fbc1-d011-4c03-ab41-dd1de3340c14",
      "kind": "label",
      "type": "text",
      "x": 0,
      "y": 270,
      "width": 180,
      "height": 20,
      "roughness": 1,
      "fontSize": 16,
      "strokeColor": "#1e1e1e",
      "version": 1,
      "versionNonce": 1670315865,
      "isDeleted": false,
      "fillStyle": "hachure",
      "strokeWidth": 1,
      "strokeStyle": "solid",
      "opacity": 100,
      "angle": 0,
      "seed": 1560149976,
      "groupIds": [],
      "frameId": null,
      "updated": 1775538137009,
      "link": null,
      "locked": false,
      "backgroundColor": "transparent",
      "fontFamily": 1,
      "roundness": null,
      "boundElements": null,
      "containerId": "c6c41d29-ac84-4806-a257-694f6e77c14b",
      "customData": {
        "mermaidId": "Active:text",
        "kind": "label"
      },
      "text": "Active",
      "textAlign": "center",
      "verticalAlign": "middle",
      "originalText": "Active",
      "lineHeight": 1.25
    },
    {
      "id": "6edc7f50-7ada-4c46-bee3-8c4ff878823c",
      "kind": "node",
      "type": "ellipse",
      "x": 75,
      "y": 390,
      "width": 30,
      "height": 30,
      "roughness": 1,
      "backgroundColor": "transparent",
      "strokeColor": "#1e1e1e",
      "strokeWidth": 1,
      "strokeStyle": "solid",
      "fillStyle": "hachure",
      "opacity": 100,
      "version": 1,
      "versionNonce": 2315251666,
      "isDeleted": false,
      "angle": 0,
      "seed": 542806123,
      "groupIds": [],
      "frameId": null,
      "updated": 1775538137009,
      "link": null,
      "locked": false,
      "fontFamily": 1,
      "roundness": null,
      "boundElements": [
        {
          "id": "af76c641-18b9-4c22-9292-461fe279c0ad",
          "type": "text"
        },
        {
          "id": "fdcd5c32-8215-4a41-8e9d-9cc909d7df6a",
          "type": "arrow"
        }
      ],
      "containerId": null,
      "customData": {
        "mermaidId": "root_end",
        "kind": "node"
      }
    },
    {
      "id": "af76c641-18b9-4c22-9292-461fe279c0ad",
      "kind": "label",
      "type": "text",
      "x": 75,
      "y": 395,
      "width": 30,
      "height": 20,
      "roughness": 1,
      "fontSize": 16,
      "strokeColor": "#1e1e1e",
      "version": 1,
      "versionNonce": 2061253397,
      "isDeleted": false,
      "fillStyle": "hachure",
      "strokeWidth": 1,
      "strokeStyle": "solid",
      "opacity": 100,
      "angle": 0,
      "seed": 1869103652,
      "groupIds": [],
      "frameId": null,
      "updated": 1775538137009,
      "link": null,
      "locked": false,
      "backgroundColor": "transparent",
      "fontFamily": 1,
      "roundness": null,
      "boundElements": null,
      "containerId": "6edc7f50-7ada-4c46-bee3-8c4ff878823c",
      "customData": {
        "mermaidId": "root_end:text",
        "kind": "label"
      },
      "text": "root_end",
      "textAlign": "center",
      "verticalAlign": "middle",
      "originalText": "root_end",
      "lineHeight": 1.25
    },
    {
      "id": "a17f86cb-d9e3-4910-b242-4bb06a34cf10",
      "kind": "edge",
      "type": "arrow",
      "x": 90,
      "y": 38,
      "width": 0,
      "height": 0,
      "roughness": 1,
      "points": [
        [
          0,
          0
        ],
        [
          0,
          64
        ]
      ],
      "startBinding": {
        "elementId": "5bde435b-3084-4783-8785-c7e895355383",
        "focus": 0,
        "gap": 8
      },
      "endBinding": {
        "elementId": "c6ac4bab-659a-440a-8c35-3247f9d17e2c",
        "focus": 0,
        "gap": 8
      },
      "strokeColor": "#1e1e1e",
      "strokeWidth": 1,
      "strokeStyle": "solid",
      "version": 1,
      "versionNonce": 1520188588,
      "isDeleted": false,
      "fillStyle": "hachure",
      "opacity": 100,
      "angle": 0,
      "seed": 617180881,
      "groupIds": [],
      "frameId": null,
      "updated": 1775538137009,
      "link": null,
      "locked": false,
      "backgroundColor": "transparent",
      "fontFamily": 1,
      "roundness": null,
      "boundElements": null,
      "containerId": null,
      "customData": {
        "mermaidId": "root_start->Idle:0",
        "kind": "edge"
      },
      "startArrowhead": null,
      "endArrowhead": "arrow"
    },
    {
      "id": "35acc28e-f29f-469f-a9ff-60aca8d8dfb7",
      "kind": "edge",
      "type": "arrow",
      "x": 90,
      "y": 178,
      "width": 0,
      "height": 0,
      "roughness": 1,
      "points": [
        [
          0,
          0
        ],
        [
          -5,
          32
        ],
        [
          0,
          64
        ]
      ],
      "startBinding": {
        "elementId": "c6ac4bab-659a-440a-8c35-3247f9d17e2c",
        "focus": 0,
        "gap": 8
      },
      "endBinding": {
        "elementId": "c6c41d29-ac84-4806-a257-694f6e77c14b",
        "focus": 0,
        "gap": 8
      },
      "strokeColor": "#1e1e1e",
      "strokeWidth": 1,
      "strokeStyle": "solid",
      "version": 1,
      "versionNonce": 3543709285,
      "isDeleted": false,
      "fillStyle": "hachure",
      "opacity": 100,
      "angle": 0,
      "seed": 139900372,
      "groupIds": [],
      "frameId": null,
      "updated": 1775538137009,
      "link": null,
      "locked": false,
      "backgroundColor": "transparent",
      "fontFamily": 1,
      "roundness": null,
      "boundElements": null,
      "containerId": null,
      "customData": {
        "mermaidId": "Idle->Active:0",
        "kind": "edge"
      },
      "startArrowhead": null,
      "endArrowhead": "arrow",
      "label": {
        "text": "start",
        "fontSize": 16
      }
    },
    {
      "id": "e2e77f92-16e6-4e37-94be-68a0309160b1",
      "kind": "edge",
      "type": "arrow",
      "x": 90,
      "y": 242,
      "width": 0,
      "height": 0,
      "roughness": 1,
      "points": [
        [
          0,
          0
        ],
        [
          5,
          -32
        ],
        [
          0,
          -64
        ]
      ],
      "startBinding": {
        "elementId": "c6c41d29-ac84-4806-a257-694f6e77c14b",
        "focus": 0,
        "gap": 8
      },
      "endBinding": {
        "elementId": "c6ac4bab-659a-440a-8c35-3247f9d17e2c",
        "focus": 0,
        "gap": 8
      },
      "strokeColor": "#1e1e1e",
      "strokeWidth": 1,
      "strokeStyle": "solid",
      "version": 1,
      "versionNonce": 3511107825,
      "isDeleted": false,
      "fillStyle": "hachure",
      "opacity": 100,
      "angle": 0,
      "seed": 657748016,
      "groupIds": [],
      "frameId": null,
      "updated": 1775538137009,
      "link": null,
      "locked": false,
      "backgroundColor": "transparent",
      "fontFamily": 1,
      "roundness": null,
      "boundElements": null,
      "containerId": null,
      "customData": {
        "mermaidId": "Active->Idle:0",
        "kind": "edge"
      },
      "startArrowhead": null,
      "endArrowhead": "arrow",
      "label": {
        "text": "stop",
        "fontSize": 16
      }
    },
    {
      "id": "fdcd5c32-8215-4a41-8e9d-9cc909d7df6a",
      "kind": "edge",
      "type": "arrow",
      "x": 90,
      "y": 318,
      "width": 0,
      "height": 0,
      "roughness": 1,
      "points": [
        [
          0,
          0
        ],
        [
          0,
          64
        ]
      ],
      "startBinding": {
        "elementId": "c6c41d29-ac84-4806-a257-694f6e77c14b",
        "focus": 0,
        "gap": 8
      },
      "endBinding": {
        "elementId": "6edc7f50-7ada-4c46-bee3-8c4ff878823c",
        "focus": 0,
        "gap": 8
      },
      "strokeColor": "#1e1e1e",
      "strokeWidth": 1,
      "strokeStyle": "solid",
      "version": 1,
      "versionNonce": 1241882233,
      "isDeleted": false,
      "fillStyle": "hachure",
      "opacity": 100,
      "angle": 0,
      "seed": 1229960184,
      "groupIds": [],
      "frameId": null,
      "updated": 1775538137009,
      "link": null,
      "locked": false,
      "backgroundColor": "transparent",
      "fontFamily": 1,
      "roundness": null,
      "boundElements": null,
      "containerId": null,
      "customData": {
        "mermaidId": "Active->root_end:0",
        "kind": "edge"
      },
      "startArrowhead": null,
      "endArrowhead": "arrow",
      "label": {
        "text": "terminate",
        "fontSize": 16
      }
    }
  ],
  "appState": {
    "viewBackgroundColor": "#ffffff"
  },
  "files": {}
}