{
  "type": "excalidraw",
  "version": 2,
  "source": "flowchart-38.mmd",
  "elements": [
    {
      "id": "d471c8a9-11d7-4bc5-bc34-543843e9c565",
      "kind": "node",
      "type": "rectangle",
      "x": 0,
      "y": 0,
      "width": 180,
      "height": 60,
      "roughness": 1,
      "backgroundColor": "transparent",
      "strokeColor": "#1e1e1e",
      "strokeWidth": 1,
      "strokeStyle": "solid",
      "fillStyle": "hachure",
      "opacity": 100,
      "version": 1,
      "versionNonce": 1430982493,
      "isDeleted": false,
      "angle": 0,
      "seed": 3289118412,
      "groupIds": [],
      "frameId": null,
      "updated": 1775750606241,
      "link": null,
      "locked": false,
      "fontFamily": 1,
      "roundness": null,
      "boundElements": [
        {
          "id": "ab6b2ea3-ccd3-402c-85e4-a8cdbd1a225b",
          "type": "text"
        },
        {
          "id": "26f891fd-ec37-4c76-accf-7fe909058da4",
          "type": "arrow"
        }
      ],
      "containerId": null,
      "customData": {
        "mermaidId": "A",
        "kind": "node"
      }
    },
    {
      "id": "ab6b2ea3-ccd3-402c-85e4-a8cdbd1a225b",
      "kind": "label",
      "type": "text",
      "x": 0,
      "y": 21,
      "width": 180,
      "height": 18,
      "roughness": 1,
      "fontSize": 14,
      "strokeColor": "#1e1e1e",
      "version": 1,
      "versionNonce": 526835652,
      "isDeleted": false,
      "fillStyle": "hachure",
      "strokeWidth": 1,
      "strokeStyle": "solid",
      "opacity": 100,
      "angle": 0,
      "seed": 277963241,
      "groupIds": [],
      "frameId": null,
      "updated": 1775750606241,
      "link": null,
      "locked": false,
      "backgroundColor": "transparent",
      "fontFamily": 1,
      "roundness": null,
      "boundElements": null,
      "containerId": "d471c8a9-11d7-4bc5-bc34-543843e9c565",
      "customData": {
        "mermaidId": "A:text",
        "kind": "label"
      },
      "text": "A",
      "textAlign": "center",
      "verticalAlign": "middle",
      "originalText": "A",
      "lineHeight": 1.25
    },
    {
      "id": "3e5abdec-4451-4936-a214-a04e51ec2a71",
      "kind": "node",
      "type": "rectangle",
      "x": 260,
      "y": 0,
      "width": 180,
      "height": 60,
      "roughness": 1,
      "backgroundColor": "transparent",
      "strokeColor": "#1e1e1e",
      "strokeWidth": 1,
      "strokeStyle": "solid",
      "fillStyle": "hachure",
      "opacity": 100,
      "version": 1,
      "versionNonce": 896260448,
      "isDeleted": false,
      "angle": 0,
      "seed": 3339451269,
      "groupIds": [],
      "frameId": null,
      "updated": 1775750606241,
      "link": null,
      "locked": false,
      "fontFamily": 1,
      "roundness": null,
      "boundElements": [
        {
          "id": "fae49deb-7f46-43d3-baa6-c96d890718ac",
          "type": "text"
        },
        {
          "id": "26f891fd-ec37-4c76-accf-7fe909058da4",
          "type": "arrow"
        },
        {
          "id": "5167fb9b-34a3-4825-bf07-5162734af96c",
          "type": "arrow"
        }
      ],
      "containerId": null,
      "customData": {
        "mermaidId": "B",
        "kind": "node"
      }
    },
    {
      "id": "fae49deb-7f46-43d3-baa6-c96d890718ac",
      "kind": "label",
      "type": "text",
      "x": 260,
      "y": 21,
      "width": 180,
      "height": 18,
      "roughness": 1,
      "fontSize": 14,
      "strokeColor": "#1e1e1e",
      "version": 1,
      "versionNonce": 3728114107,
      "isDeleted": false,
      "fillStyle": "hachure",
      "strokeWidth": 1,
      "strokeStyle": "solid",
      "opacity": 100,
      "angle": 0,
      "seed": 2597571446,
      "groupIds": [],
      "frameId": null,
      "updated": 1775750606241,
      "link": null,
      "locked": false,
      "backgroundColor": "transparent",
      "fontFamily": 1,
      "roundness": null,
      "boundElements": null,
      "containerId": "3e5abdec-4451-4936-a214-a04e51ec2a71",
      "customData": {
        "mermaidId": "B:text",
        "kind": "label"
      },
      "text": "B",
      "textAlign": "center",
      "verticalAlign": "middle",
      "originalText": "B",
      "lineHeight": 1.25
    },
    {
      "id": "795f2353-7c1d-4524-a96f-78e00ec71749",
      "kind": "node",
      "type": "rectangle",
      "x": 520,
      "y": 0,
      "width": 180,
      "height": 60,
      "roughness": 1,
      "backgroundColor": "transparent",
      "strokeColor": "#1e1e1e",
      "strokeWidth": 1,
      "strokeStyle": "solid",
      "fillStyle": "hachure",
      "opacity": 100,
      "version": 1,
      "versionNonce": 1706025303,
      "isDeleted": false,
      "angle": 0,
      "seed": 3322673650,
      "groupIds": [],
      "frameId": null,
      "updated": 1775750606241,
      "link": null,
      "locked": false,
      "fontFamily": 1,
      "roundness": null,
      "boundElements": [
        {
          "id": "bd87bf08-fba7-4edc-a212-a5cf6c7f2d1e",
          "type": "text"
        },
        {
          "id": "5167fb9b-34a3-4825-bf07-5162734af96c",
          "type": "arrow"
        },
        {
          "id": "9116009a-32ea-4cc6-ac26-366877d33a54",
          "type": "arrow"
        }
      ],
      "containerId": null,
      "customData": {
        "mermaidId": "C",
        "kind": "node"
      }
    },
    {
      "id": "bd87bf08-fba7-4edc-a212-a5cf6c7f2d1e",
      "kind": "label",
      "type": "text",
      "x": 520,
      "y": 21,
      "width": 180,
      "height": 18,
      "roughness": 1,
      "fontSize": 14,
      "strokeColor": "#1e1e1e",
      "version": 1,
      "versionNonce": 1258212198,
      "isDeleted": false,
      "fillStyle": "hachure",
      "strokeWidth": 1,
      "strokeStyle": "solid",
      "opacity": 100,
      "angle": 0,
      "seed": 3501613375,
      "groupIds": [],
      "frameId": null,
      "updated": 1775750606241,
      "link": null,
      "locked": false,
      "backgroundColor": "transparent",
      "fontFamily": 1,
      "roundness": null,
      "boundElements": null,
      "containerId": "795f2353-7c1d-4524-a96f-78e00ec71749",
      "customData": {
        "mermaidId": "C:text",
        "kind": "label"
      },
      "text": "C",
      "textAlign": "center",
      "verticalAlign": "middle",
      "originalText": "C",
      "lineHeight": 1.25
    },
    {
      "id": "8c8e912b-637c-4f48-b8f6-0d06f3aeda3b",
      "kind": "node",
      "type": "rectangle",
      "x": 780,
      "y": 0,
      "width": 180,
      "height": 60,
      "roughness": 1,
      "backgroundColor": "transparent",
      "strokeColor": "#1e1e1e",
      "strokeWidth": 1,
      "strokeStyle": "solid",
      "fillStyle": "hachure",
      "opacity": 100,
      "version": 1,
      "versionNonce": 3959726874,
      "isDeleted": false,
      "angle": 0,
      "seed": 3238785555,
      "groupIds": [],
      "frameId": null,
      "updated": 1775750606241,
      "link": null,
      "locked": false,
      "fontFamily": 1,
      "roundness": null,
      "boundElements": [
        {
          "id": "1d1cc594-9db4-449a-857c-c168a74bfc67",
          "type": "text"
        },
        {
          "id": "9116009a-32ea-4cc6-ac26-366877d33a54",
          "type": "arrow"
        }
      ],
      "containerId": null,
      "customData": {
        "mermaidId": "D",
        "kind": "node"
      }
    },
    {
      "id": "1d1cc594-9db4-449a-857c-c168a74bfc67",
      "kind": "label",
      "type": "text",
      "x": 780,
      "y": 21,
      "width": 180,
      "height": 18,
      "roughness": 1,
      "fontSize": 14,
      "strokeColor": "#1e1e1e",
      "version": 1,
      "versionNonce": 3360435821,
      "isDeleted": false,
      "fillStyle": "hachure",
      "strokeWidth": 1,
      "strokeStyle": "solid",
      "opacity": 100,
      "angle": 0,
      "seed": 4072434364,
      "groupIds": [],
      "frameId": null,
      "updated": 1775750606241,
      "link": null,
      "locked": false,
      "backgroundColor": "transparent",
      "fontFamily": 1,
      "roundness": null,
      "boundElements": null,
      "containerId": "8c8e912b-637c-4f48-b8f6-0d06f3aeda3b",
      "customData": {
        "mermaidId": "D:text",
        "kind": "label"
      },
      "text": "D",
      "textAlign": "center",
      "verticalAlign": "middle",
      "originalText": "D",
      "lineHeight": 1.25
    },
    {
      "id": "26f891fd-ec37-4c76-accf-7fe909058da4",
      "kind": "edge",
      "type": "arrow",
      "x": 188,
      "y": 30,
      "width": 0,
      "height": 0,
      "roughness": 1,
      "points": [
        [
          0,
          0
        ],
        [
          64,
          0
        ]
      ],
      "startBinding": {
        "elementId": "d471c8a9-11d7-4bc5-bc34-543843e9c565",
        "focus": 0,
        "gap": 8
      },
      "endBinding": {
        "elementId": "3e5abdec-4451-4936-a214-a04e51ec2a71",
        "focus": 0,
        "gap": 8
      },
      "arrowheadStart": null,
      "arrowheadEnd": "arrow",
      "strokeColor": "#1e1e1e",
      "strokeWidth": 1,
      "strokeStyle": "solid",
      "version": 1,
      "versionNonce": 2169863944,
      "isDeleted": false,
      "fillStyle": "hachure",
      "opacity": 100,
      "angle": 0,
      "seed": 1863367533,
      "groupIds": [],
      "frameId": null,
      "updated": 1775750606241,
      "link": null,
      "locked": false,
      "backgroundColor": "transparent",
      "fontFamily": 1,
      "roundness": null,
      "boundElements": null,
      "containerId": null,
      "customData": {
        "mermaidId": "A->B:0",
        "kind": "edge"
      },
      "startArrowhead": null,
      "endArrowhead": "arrow"
    },
    {
      "id": "5167fb9b-34a3-4825-bf07-5162734af96c",
      "kind": "edge",
      "type": "arrow",
      "x": 448,
      "y": 30,
      "width": 0,
      "height": 0,
      "roughness": 1,
      "points": [
        [
          0,
          0
        ],
        [
          64,
          0
        ]
      ],
      "startBinding": {
        "elementId": "3e5abdec-4451-4936-a214-a04e51ec2a71",
        "focus": 0,
        "gap": 8
      },
      "endBinding": {
        "elementId": "795f2353-7c1d-4524-a96f-78e00ec71749",
        "focus": 0,
        "gap": 8
      },
      "arrowheadStart": null,
      "arrowheadEnd": "arrow",
      "strokeColor": "#1e1e1e",
      "strokeWidth": 1,
      "strokeStyle": "solid",
      "version": 1,
      "versionNonce": 2595334284,
      "isDeleted": false,
      "fillStyle": "hachure",
      "opacity": 100,
      "angle": 0,
      "seed": 1905092657,
      "groupIds": [],
      "frameId": null,
      "updated": 1775750606241,
      "link": null,
      "locked": false,
      "backgroundColor": "transparent",
      "fontFamily": 1,
      "roundness": null,
      "boundElements": null,
      "containerId": null,
      "customData": {
        "mermaidId": "B->C:0",
        "kind": "edge"
      },
      "startArrowhead": null,
      "endArrowhead": "arrow"
    },
    {
      "id": "9116009a-32ea-4cc6-ac26-366877d33a54",
      "kind": "edge",
      "type": "arrow",
      "x": 708,
      "y": 30,
      "width": 0,
      "height": 0,
      "roughness": 1,
      "points": [
        [
          0,
          0
        ],
        [
          64,
          0
        ]
      ],
      "startBinding": {
        "elementId": "795f2353-7c1d-4524-a96f-78e00ec71749",
        "focus": 0,
        "gap": 8
      },
      "endBinding": {
        "elementId": "8c8e912b-637c-4f48-b8f6-0d06f3aeda3b",
        "focus": 0,
        "gap": 8
      },
      "arrowheadStart": null,
      "arrowheadEnd": "arrow",
      "strokeColor": "#1e1e1e",
      "strokeWidth": 1,
      "strokeStyle": "solid",
      "version": 1,
      "versionNonce": 2224471520,
      "isDeleted": false,
      "fillStyle": "hachure",
      "opacity": 100,
      "angle": 0,
      "seed": 3824952325,
      "groupIds": [],
      "frameId": null,
      "updated": 1775750606241,
      "link": null,
      "locked": false,
      "backgroundColor": "transparent",
      "fontFamily": 1,
      "roundness": null,
      "boundElements": null,
      "containerId": null,
      "customData": {
        "mermaidId": "C->D:0",
        "kind": "edge"
      },
      "startArrowhead": null,
      "endArrowhead": "arrow"
    }
  ],
  "appState": {
    "viewBackgroundColor": "#ffffff"
  },
  "files": {}
}